py24talk/__init__.py
py24talk/badge.py
py24talk/badge.pyi
py24talk/content.py
py24talk/content.pyi
py24talk/exceptions/__init__.py
py24talk/exceptions/not_found.py
py24talk/exceptions/unknown_error.py
py24talk/managers/requests.py
py24talk/post.py
py24talk/post.pyi
py24talk/topic.py
py24talk/topic.pyi
py24talk/user.py
py24talk/user.pyi
py24talk-0.0.6.dist-info/LICENSE
py24talk-0.0.6.dist-info/METADATA
py24talk-0.0.6.dist-info/WHEEL
py24talk-0.0.6.dist-info/RECORD
